MANIFEST.in
comp.sh
setup.py
tglinker.py
tglinker.egg-info/PKG-INFO
tglinker.egg-info/SOURCES.txt
tglinker.egg-info/dependency_links.txt
tglinker.egg-info/entry_points.txt
tglinker.egg-info/top_level.txt