Metadata-Version: 1.0
Name: tglinker
Version: 0.5
Summary: TurboGears EC2 symlink Generation Tool
Home-page: UNKNOWN
Author: Michael J. Pedersen
Author-email: m.pedersen@icelus.org
License: UNKNOWN
Platform: UNKNOWN
